[
    {
        "imageName": "empty",
        "originScale": 1,
        "originAngle": 0,
        "originFrameX": 0,
        "originFrameY": 464,
        "originFrameWidth": 375,
        "originFrameHeight": 127,
        "gesScale": 1,
        "gesRotation": 0,
        "isBgImage": true,
        "overlayRectX": 0,
        "overlayRectY": 0,
        "overlayRectWidth": 1,
        "overlayRectHeight": 1,
        "imageType": "square",
        "bgAddImageType":"Christmas09-sticker-03"
    },
    {
        "imageName": "Christmas02-sticker-bg01",
        "originScale": 1,
        "originAngle": 0,
        "originFrameX": -15,
        "originFrameY": 114,
        "originFrameWidth": 380,
        "originFrameHeight": 500,
        "gesScale": 1,
        "gesRotation": 0,
        "overlayRectX": 0.15,
        "overlayRectY": 0.12,
        "overlayRectWidth": 0.77,
        "overlayRectHeight": 0.73,
        "imageType": "square",
        "isBgImage": true,
        "bgAddImageType":"Christmas02-sticker-add00"
    },
    {
        "imageName": "empty",
        "originScale": 1,
        "originAngle": 0,
        "originFrameX": 108,
        "originFrameY": 13,
        "originFrameWidth": 159,
        "originFrameHeight": 88,
        "gesScale": 1,
        "gesRotation": 0,
        "isBgImage": true,
        "overlayRectX": 0,
        "overlayRectY": 0,
        "overlayRectWidth": 1,
        "overlayRectHeight": 1,
        "imageType": "square",
        "bgAddImageType":"Christmas09-sticker-01"
    },
    {
        "imageName": "empty",
        "originScale": 1,
        "originAngle": 0,
        "originFrameX": 12.5,
        "originFrameY": 19,
        "originFrameWidth": 350,
        "originFrameHeight": 446,
        "gesScale": 1,
        "gesRotation": 0,
        "isBgImage": true,
        "overlayRectX": 0,
        "overlayRectY": 0,
        "overlayRectWidth": 1,
        "overlayRectHeight": 1,
        "imageType": "square",
        "bgAddImageType":"Christmas09-sticker-02"
    },
    {
        "imageName": "empty",
        "originScale": 1,
        "originAngle": 0,
        "originFrameX": 0,
        "originFrameY": 480,
        "originFrameWidth": 375,
        "originFrameHeight": 111,
        "gesScale": 1,
        "gesRotation": 0,
        "isBgImage": true,
        "overlayRectX": 0,
        "overlayRectY": 0,
        "overlayRectWidth": 1,
        "overlayRectHeight": 1,
        "imageType": "square",
        "bgAddImageType":"Christmas09-sticker-05"
    },
    {
        "imageName": "empty",
        "originScale": 1,
        "originAngle": 0,
        "originFrameX": 22.5,
        "originFrameY": 112,
        "originFrameWidth": 330,
        "originFrameHeight": 133,
        "gesScale": 1,
        "gesRotation": 0,
        "isBgImage": true,
        "overlayRectX": 0,
        "overlayRectY": 0,
        "overlayRectWidth": 1,
        "overlayRectHeight": 1,
        "imageType": "square",
        "bgAddImageType":"Christmas09-sticker-04"
    }]
 
